[
  {
    "Id": "00000000-0000-0000-0000-000000000001",
    "Name": "Базовый режим",
    "Mode": "Global",
    "CreatedAt": "2026-02-01T08:00:00+00:00",
    "UpdatedAt": "2026-02-01T08:00:00+00:00",
    "Radio": {
      "Antenna": {
        "IsPresent": true,
        "IsRelevant": true,
        "Parameters": [],
        "Sections": [],
        "AntennaId": "ANT-001",
        "Tuning": [],
        "Reference": [
          { "Key": "Антенна", "Value": "АРК-3" },
          { "Key": "МШПР", "Value": "МШПР-0408" },
          { "Key": "Диапазон", "Value": "4.00-5.00 ГГц" },
          { "Key": "Поляризация", "Value": "V" }
        ]
      },
      "Rpu": {
        "IsPresent": true,
        "IsRelevant": true,
        "Parameters": [
          { "Key": "Частота приемника, кГц", "Value": "349995.059" },
          { "Key": "Аттенюатор", "Value": "0" },
          { "Key": "Перегруз АЦП", "Value": "0" }
        ],
        "Sections": []
      },
      "Detector": {
        "IsPresent": true,
        "IsRelevant": true,
        "Parameters": [
          { "Key": "Несущая частота, кГц", "Value": "349995.148" },
          { "Key": "Тактовая частота, кГц", "Value": "6099.998" },
          { "Key": "ФАПЧ", "Value": "1/400" },
          { "Key": "Фильтр", "Value": "0.4" },
          { "Key": "Корректор", "Value": "Отключен" }
        ],
        "Sections": []
      },
      "Demodulator": {
        "IsPresent": true,
        "IsRelevant": true,
        "Parameters": [
          { "Key": "Кодер", "Value": "ISU2" },
          { "Key": "Модуляция", "Value": "ACM" },
          { "Key": "Пилоты", "Value": "..." },
          { "Key": "Инверсия спектра", "Value": "Вкл" },
          { "Key": "ОСШ", "Value": "29.6" }
        ],
        "Sections": []
      },
      "Decoder": {
        "IsPresent": true,
        "IsRelevant": true,
        "Parameters": [
          { "Key": "Кодер", "Value": "ISU2" },
          { "Key": "Итераций", "Value": "127" },
          { "Key": "Температура", "Value": "46" },
          { "Key": "Сигнатура", "Value": "Вкл" }
        ],
        "Sections": []
      }
    }
  },
  {
    "Id": "00000000-0000-0000-0000-000000000002",
    "Name": "Режим мониторинга",
    "Mode": "Observe",
    "CreatedAt": "2026-02-02T10:30:00+00:00",
    "UpdatedAt": "2026-02-02T10:30:00+00:00",
    "Radio": {
      "Antenna": {
        "IsPresent": true,
        "IsRelevant": false,
        "Parameters": [],
        "Sections": [],
        "AntennaId": "ANT-014",
        "Tuning": [],
        "Reference": [
          { "Key": "Антенна", "Value": "АРК-3" },
          { "Key": "МШПР", "Value": "МШПР-0408" },
          { "Key": "Диапазон", "Value": "4.00-5.00 ГГц" },
          { "Key": "Поляризация", "Value": "V" }
        ]
      },
      "Rpu": {
        "IsPresent": true,
        "IsRelevant": true,
        "Parameters": [
          { "Key": "Частота приемника, кГц", "Value": "349995.150" },
          { "Key": "Аттенюатор", "Value": "0" },
          { "Key": "Перегруз АЦП", "Value": "0" }
        ],
        "Sections": []
      },
      "Detector": {
        "IsPresent": true,
        "IsRelevant": true,
        "Parameters": [
          { "Key": "Несущая частота, кГц", "Value": "349995.148" },
          { "Key": "Тактовая частота, кГц", "Value": "6099.998" },
          { "Key": "ФАПЧ", "Value": "1/400" },
          { "Key": "Фильтр", "Value": "0.4" },
          { "Key": "Корректор", "Value": "Отключен" }
        ],
        "Sections": []
      },
      "Demodulator": {
        "IsPresent": true,
        "IsRelevant": false,
        "Parameters": [],
        "Sections": []
      },
      "Decoder": {
        "IsPresent": false,
        "IsRelevant": false,
        "Parameters": [],
        "Sections": []
      }
    }
  }
]
